testgres/common/exceptions.py
testgres_common-0.0.4.dist-info/licenses/LICENSE
testgres_common-0.0.4.dist-info/METADATA
testgres_common-0.0.4.dist-info/WHEEL
testgres_common-0.0.4.dist-info/top_level.txt
testgres_common-0.0.4.dist-info/RECORD
