Metadata-Version: 2.4
Name: testgres.common
Version: 0.0.4
Summary: Testgres common code
Author-email: Postgres Professional <testgres@postgrespro.ru>
License: PostgreSQL
Project-URL: HomePage, https://github.com/postgrespro/testgres.common
Keywords: testgres
Classifier: Intended Audience :: Developers
Classifier: Operating System :: Unix
Classifier: Programming Language :: Python :: 3 :: Only
Classifier: Programming Language :: Python :: 3.7
Classifier: Programming Language :: Python :: 3.8
Classifier: Programming Language :: Python :: 3.9
Classifier: Programming Language :: Python :: 3.10
Classifier: Programming Language :: Python :: 3.11
Classifier: Programming Language :: Python :: 3.12
Classifier: Programming Language :: Python :: 3.13
Classifier: Programming Language :: Python :: 3.14
Classifier: Topic :: Software Development :: Libraries
Classifier: Topic :: Software Development :: Testing
Requires-Python: >=3.7.17
License-File: LICENSE
Dynamic: license-file
